{
    "name": "Notification",
    "description": "Notification targeting a single user.",
    "layout": {
        "groups": [
            {
                "sections": [
                    {
                        "rows": [
                            {
                                "columns": [
                                    {
                                        "width": "50%",
                                        "align": "left",
                                        "items": [
                                            {
                                                "type": "field",
                                                "value": "title",
                                                "width": "100%",
                                                "widget": {
                                                    "heading": true
                                                }
                                            }
                                        ]
                                    },
                                    {
                                        "width": "25%",
                                        "items": []
                                    },
                                    {
                                        "width": "25%",
                                        "items": [
                                            {
                                                "type": "field",
                                                "value": "user_id",
                                                "width": "100%"
                                            },
                                            {
                                                "type": "field",
                                                "value": "status",
                                                "width": "100%"
                                            }
                                        ]
                                    }
                                ]
                            },
                            {
                                "columns": [
                                    {
                                        "width": "50%",
                                        "align": "left",
                                        "items": [
                                            {
                                                "type": "field",
                                                "value": "message",
                                                "width": "100%"
                                            }
                                        ]
                                    },
                                    {
                                        "width": "25%",
                                        "items": []
                                    },
                                    {
                                        "width": "25%",
                                        "items": [
                                            {
                                                "type": "field",
                                                "value": "is_persistent",
                                                "width": "100%"
                                            },
                                            {
                                                "type": "field",
                                                "value": "remind_frequency",
                                                "width": "100%"
                                            }
                                        ]
                                    }
                                ]
                            }
                        ]
                    }
                ]
            }
        ]
    }
}
